blockex/__init__.py
blockex/tradeapi/__init__.py
blockex/tradeapi/apiclient.py
blockex/tradeapi/auth.py
blockex/tradeapi/helper.py
blockex/tradeapi/interface.py
blockex/tradeapi/tradeapi.py
blockex.trade_sdk-0.1.1.dist-info/METADATA
blockex.trade_sdk-0.1.1.dist-info/RECORD
blockex.trade_sdk-0.1.1.dist-info/WHEEL
blockex.trade_sdk-0.1.1.dist-info/top_level.txt
